MANIFEST.in
README.rst
setup.cfg
setup.py
bearychat/__init__.py
bearychat/incoming.py
bearychat/model.py
bearychat/rtm_client.py
bearychat/rtm_client_service.py
bearychat/rtm_message.py
bearychat.egg-info/PKG-INFO
bearychat.egg-info/SOURCES.txt
bearychat.egg-info/dependency_links.txt
bearychat.egg-info/requires.txt
bearychat.egg-info/top_level.txt
bearychat/openapi/__init__.py
bearychat/openapi/_api.py
bearychat/openapi/client.py
tests/__init__.py
tests/conftest.py
tests/test_incoming.py
tests/test_model.py